[
  {
    "title": "TEst 3 updated",
    "oneliner": "Integration tool testing article",
    "url": "article-2",
    "tags": [
      "test",
      "integration"
    ],
    "date": "2022-02-21T14:36:50.406Z",
    "filePath": "C:\\code\\Owned\\thepeachspeech-tool\\mock\\article.md"
  },
  {
    "filePath": "C:\\code\\Owned\\thepeachspeech-tool\\mock\\article.md",
    "title": "Article 4",
    "oneliner": "dfdsfdf",
    "url": "article-4",
    "tags": [
      "dl",
      "dl"
    ],
    "date": "1970-01-01T00:00:00.000Z"
  },
  {
    "title": "Mocking the logger",
    "oneliner": "Presenting Mogger, the definitive solution for logging mocking and assertions in .NET",
    "url": "mocking-the-logger",
    "tags": [
      ".net",
      "xunit",
      "logging",
      "testing"
    ],
    "date": "2022-04-06T08:26:32.283Z"
  }
]